odoo10_addon_pos_margin-10.0.1.0.1-py3.8-nspkg.pth
odoo/addons/pos_margin/README.rst
odoo/addons/pos_margin/__init__.py
odoo/addons/pos_margin/__manifest__.py
odoo/addons/pos_margin/i18n/ca.po
odoo/addons/pos_margin/i18n/es.po
odoo/addons/pos_margin/i18n/fr.po
odoo/addons/pos_margin/i18n/it.po
odoo/addons/pos_margin/i18n/nl_NL.po
odoo/addons/pos_margin/i18n/pos_margin.pot
odoo/addons/pos_margin/models/__init__.py
odoo/addons/pos_margin/models/pos_order.py
odoo/addons/pos_margin/models/pos_order_line.py
odoo/addons/pos_margin/static/description/icon.png
odoo/addons/pos_margin/static/description/pos_order_form.png
odoo/addons/pos_margin/views/view_pos_order.xml
odoo10_addon_pos_margin-10.0.1.0.1.dist-info/METADATA
odoo10_addon_pos_margin-10.0.1.0.1.dist-info/WHEEL
odoo10_addon_pos_margin-10.0.1.0.1.dist-info/namespace_packages.txt
odoo10_addon_pos_margin-10.0.1.0.1.dist-info/top_level.txt
odoo10_addon_pos_margin-10.0.1.0.1.dist-info/RECORD
